parse_hcl/__init__.py
parse_hcl/cli.py
parse_hcl/parsers/__init__.py
parse_hcl/parsers/generic_parser.py
parse_hcl/parsers/locals_parser.py
parse_hcl/parsers/output_parser.py
parse_hcl/parsers/variable_parser.py
parse_hcl/services/__init__.py
parse_hcl/services/artifact_parsers.py
parse_hcl/services/terraform_json_parser.py
parse_hcl/services/terraform_parser.py
parse_hcl/types/__init__.py
parse_hcl/utils/__init__.py
parse_hcl/utils/output_metadata.py
parse_hcl/utils/common/__init__.py
parse_hcl/utils/common/errors.py
parse_hcl/utils/common/fs.py
parse_hcl/utils/common/logger.py
parse_hcl/utils/common/value_helpers.py
parse_hcl/utils/graph/__init__.py
parse_hcl/utils/graph/graph_builder.py
parse_hcl/utils/lexer/__init__.py
parse_hcl/utils/lexer/block_scanner.py
parse_hcl/utils/lexer/hcl_lexer.py
parse_hcl/utils/parser/__init__.py
parse_hcl/utils/parser/body_parser.py
parse_hcl/utils/parser/value_classifier.py
parse_hcl/utils/serialization/__init__.py
parse_hcl/utils/serialization/serializer.py
parse_hcl/utils/serialization/yaml.py
parse_hcl-1.0.0.dist-info/METADATA
parse_hcl-1.0.0.dist-info/WHEEL
parse_hcl-1.0.0.dist-info/entry_points.txt
parse_hcl-1.0.0.dist-info/top_level.txt
parse_hcl-1.0.0.dist-info/RECORD
