Metadata-Version: 2.4
Name: parse-hcl
Version: 1.0.0
Summary: CLI-first Terraform/HCL parser for Python with JSON/YAML output, dependency graphs, and per-file metadata.
Author-email: Juan Lee <juan.lee@sigmoid.us>
License: Apache-2.0
Project-URL: Homepage, https://github.com/sigmoid-hq/parse-hcl
Project-URL: Repository, https://github.com/sigmoid-hq/parse-hcl
Keywords: terraform,hcl,terraform parser,iac,infrastructure-as-code,tfvars,tfstate,plan,plan.json,cli,json,yaml,dependency graph,static analysis
Classifier: License :: OSI Approved :: Apache Software License
Classifier: Programming Language :: Python
Classifier: Programming Language :: Python :: 3
Classifier: Programming Language :: Python :: 3 :: Only
Classifier: Programming Language :: Python :: 3.9
Classifier: Programming Language :: Python :: 3.10
Classifier: Programming Language :: Python :: 3.11
Classifier: Programming Language :: Python :: 3.12
Classifier: Intended Audience :: Developers
Classifier: Topic :: Software Development :: Libraries
Classifier: Topic :: Utilities
Requires-Python: >=3.9
